playingcards/__init__.py
playingcards/card.py
playingcards/deck.py
playingcards.py-1.0.1.dist-info/LICENSE
playingcards.py-1.0.1.dist-info/METADATA
playingcards.py-1.0.1.dist-info/WHEEL
playingcards.py-1.0.1.dist-info/top_level.txt
playingcards.py-1.0.1.dist-info/RECORD
