Metadata-Version: 2.1
Name: playingcards.py
Version: 1.0.1
Summary: An Advanced Python Playing Card Module that makes creating playing card games simple and easy!
Home-page: https://github.com/Prodxgy/playingcards.py
Author: Prodxgy
License: MIT
Platform: UNKNOWN
Classifier: License :: OSI Approved :: MIT License
Classifier: Programming Language :: Python :: 3.6
Classifier: Programming Language :: Python :: 3.7
Classifier: Programming Language :: Python :: 3.8
Classifier: Programming Language :: Python :: 3.9
Requires-Python: >=3.6.0
